{
  "accentColor": "{{appsmith.theme.colors.primaryColor}}",
  "animateLoading": true,
  "borderRadius": "{{appsmith.theme.borderRadius.appBorderRadius}}",
  "bottomRow": 41,
  "boxShadow": "none",
  "closeOnSelection": true,
  "dateFormat": "YYYY-MM-DD HH:mm",
  "datePickerType": "DATE_PICKER",
  "defaultDate": "2024-08-26T11:58:52.481Z",
  "dynamicBindingPathList": [
    {
      "key": "accentColor"
    },
    {
      "key": "borderRadius"
    }
  ],
  "dynamicHeight": "FIXED",
  "firstDayOfWeek": 0,
  "isDisabled": false,
  "isLoading": false,
  "isRequired": false,
  "isVisible": true,
  "key": "abja7pgsl8",
  "label": "Label",
  "labelAlignment": "left",
  "labelPosition": "Top",
  "labelTextSize": "0.875rem",
  "labelWidth": 5,
  "leftColumn": 3,
  "maxDate": "2121-12-31T18:29:00.000Z",
  "maxDynamicHeight": 9000,
  "minDate": "1920-12-31T18:30:00.000Z",
  "minDynamicHeight": 4,
  "minWidth": 450,
  "mobileBottomRow": 44,
  "mobileLeftColumn": 0,
  "mobileRightColumn": 20,
  "mobileTopRow": 37,
  "needsErrorInfo": false,
  "parentColumnSpace": 14.15625,
  "parentId": "0",
  "parentRowSpace": 10,
  "renderMode": "CANVAS",
  "responsiveBehavior": "fill",
  "rightColumn": 23,
  "shortcuts": false,
  "timePrecision": "minute",
  "topRow": 34,
  "type": "DATE_PICKER_WIDGET2",
  "version": 2,
  "widgetId": "87nt0ltxem",
  "widgetName": "DatePicker1"
}